py_asciimath/__init__.py
py_asciimath/__main__.py
py_asciimath/const.py
py_asciimath/py_asciimath.py
py_asciimath/dtd/mathml1/isoamsa.ent
py_asciimath/dtd/mathml1/isoamsb.ent
py_asciimath/dtd/mathml1/isoamsc.ent
py_asciimath/dtd/mathml1/isoamsn.ent
py_asciimath/dtd/mathml1/isoamso.ent
py_asciimath/dtd/mathml1/isoamsr.ent
py_asciimath/dtd/mathml1/isobox.ent
py_asciimath/dtd/mathml1/isocyr1.ent
py_asciimath/dtd/mathml1/isocyr2.ent
py_asciimath/dtd/mathml1/isodia.ent
py_asciimath/dtd/mathml1/isogrk1.ent
py_asciimath/dtd/mathml1/isogrk2.ent
py_asciimath/dtd/mathml1/isogrk3.ent
py_asciimath/dtd/mathml1/isogrk4.ent
py_asciimath/dtd/mathml1/isolat1.ent
py_asciimath/dtd/mathml1/isolat2.ent
py_asciimath/dtd/mathml1/isomfrk.ent
py_asciimath/dtd/mathml1/isomopf.ent
py_asciimath/dtd/mathml1/isomscr.ent
py_asciimath/dtd/mathml1/isonum.ent
py_asciimath/dtd/mathml1/isopub.ent
py_asciimath/dtd/mathml1/isotech.ent
py_asciimath/dtd/mathml1/mathml1.dtd
py_asciimath/dtd/mathml1/mmlalias.ent
py_asciimath/dtd/mathml1/mmlextra.ent
py_asciimath/dtd/mathml2/mathml2-qname-1.mod
py_asciimath/dtd/mathml2/mathml2.dtd
py_asciimath/dtd/mathml2/xhtml-math11-f.dtd
py_asciimath/dtd/mathml2/html/lat1.ent
py_asciimath/dtd/mathml2/html/special.ent
py_asciimath/dtd/mathml2/html/symbol.ent
py_asciimath/dtd/mathml2/iso8879/isoamsa.ent
py_asciimath/dtd/mathml2/iso8879/isoamsb.ent
py_asciimath/dtd/mathml2/iso8879/isoamsc.ent
py_asciimath/dtd/mathml2/iso8879/isoamsn.ent
py_asciimath/dtd/mathml2/iso8879/isoamso.ent
py_asciimath/dtd/mathml2/iso8879/isoamsr.ent
py_asciimath/dtd/mathml2/iso8879/isobox.ent
py_asciimath/dtd/mathml2/iso8879/isocyr1.ent
py_asciimath/dtd/mathml2/iso8879/isocyr2.ent
py_asciimath/dtd/mathml2/iso8879/isodia.ent
py_asciimath/dtd/mathml2/iso8879/isogrk1.ent
py_asciimath/dtd/mathml2/iso8879/isogrk2.ent
py_asciimath/dtd/mathml2/iso8879/isogrk3.ent
py_asciimath/dtd/mathml2/iso8879/isogrk4.ent
py_asciimath/dtd/mathml2/iso8879/isolat1.ent
py_asciimath/dtd/mathml2/iso8879/isolat2.ent
py_asciimath-0.2.5.dist-info/LICENSE
py_asciimath-0.2.5.dist-info/METADATA
py_asciimath-0.2.5.dist-info/WHEEL
py_asciimath-0.2.5.dist-info/entry_points.txt
py_asciimath-0.2.5.dist-info/top_level.txt
py_asciimath-0.2.5.dist-info/RECORD
