Metadata-Version: 2.1
Name: py-asciimath
Version: 0.2.5
Summary: A simple converter from ASCIIMath/MathML to LaTeX/MathML
Home-page: https://github.com/belerico/py-asciimath
Author: Federico Belotti
Author-email: belo.fede@outlook.com
License: UNKNOWN
Platform: UNKNOWN
Classifier: License :: OSI Approved :: MIT License
Classifier: Programming Language :: Python :: 3
Classifier: Programming Language :: Python :: 3.5
Classifier: Programming Language :: Python :: 3.6
Classifier: Programming Language :: Python :: 3.7
Classifier: Programming Language :: Python :: 3.8
Classifier: Programming Language :: Python :: 3.9
Requires-Dist: lark-parser
Requires-Dist: docopt
Requires-Dist: lxml
